{
  "main": {
    "id": "665f1f0fd6103637",
    "type": "split",
    "children": [
      {
        "id": "defe46af7904c430",
        "type": "tabs",
        "children": [
          {
            "id": "1d366ad5f97b089f",
            "type": "leaf",
            "state": {
              "type": "empty",
              "state": {}
            }
          }
        ]
      }
    ],
    "direction": "vertical"
  },
  "left": {
    "id": "8b85a42affabe3f0",
    "type": "split",
    "children": [
      {
        "id": "691d5b955e325ad7",
        "type": "tabs",
        "children": [
          {
            "id": "b4081df31b073ba1",
            "type": "leaf",
            "state": {
              "type": "file-explorer",
              "state": {
                "sortOrder": "alphabetical"
              }
            }
          },
          {
            "id": "7651b309df35f977",
            "type": "leaf",
            "state": {
              "type": "search",
              "state": {
                "query": "",
                "matchingCase": false,
                "explainSearch": false,
                "collapseAll": false,
                "extraContext": false,
                "sortOrder": "alphabetical"
              }
            }
          },
          {
            "id": "5a622b64d17e1395",
            "type": "leaf",
            "state": {
              "type": "starred",
              "state": {}
            }
          },
          {
            "id": "88661c494012697a",
            "type": "leaf",
            "state": {
              "type": "bookmarks",
              "state": {}
            }
          }
        ]
      }
    ],
    "direction": "horizontal",
    "width": 378.5
  },
  "right": {
    "id": "473d8e5f79eb7c16",
    "type": "split",
    "children": [
      {
        "id": "cffa5d859dba8328",
        "type": "tabs",
        "children": [
          {
            "id": "b0107b3ed3d883f1",
            "type": "leaf",
            "state": {
              "type": "localgraph",
              "state": {
                "options": {
                  "collapse-filter": true,
                  "search": "",
                  "localJumps": 1,
                  "localBacklinks": true,
                  "localForelinks": true,
                  "localInterlinks": false,
                  "showTags": false,
                  "showAttachments": false,
                  "hideUnresolved": false,
                  "collapse-color-groups": true,
                  "colorGroups": [],
                  "collapse-display": true,
                  "showArrow": false,
                  "textFadeMultiplier": 0,
                  "nodeSizeMultiplier": 1,
                  "lineSizeMultiplier": 1,
                  "collapse-forces": true,
                  "centerStrength": 0.518713248970312,
                  "repelStrength": 10,
                  "linkStrength": 1,
                  "linkDistance": 250,
                  "scale": 1,
                  "close": true
                }
              }
            }
          },
          {
            "id": "1be8427d9468f627",
            "type": "leaf",
            "state": {
              "type": "backlink",
              "state": {
                "collapseAll": false,
                "extraContext": false,
                "sortOrder": "alphabetical",
                "showSearch": false,
                "searchQuery": "",
                "backlinkCollapsed": false,
                "unlinkedCollapsed": true
              }
            }
          },
          {
            "id": "46e538965bf537f1",
            "type": "leaf",
            "state": {
              "type": "outgoing-link",
              "state": {
                "linksCollapsed": false,
                "unlinkedCollapsed": true
              }
            }
          },
          {
            "id": "ea2627dedeb2d60e",
            "type": "leaf",
            "state": {
              "type": "tag",
              "state": {
                "sortOrder": "frequency",
                "useHierarchy": false
              }
            }
          },
          {
            "id": "2213cfa37f7fe47b",
            "type": "leaf",
            "state": {
              "type": "outline",
              "state": {}
            }
          }
        ]
      }
    ],
    "direction": "horizontal",
    "width": 358.5
  },
  "left-ribbon": {
    "hiddenItems": {
      "daily-notes:Open today's daily note": false,
      "switcher:Open quick switcher": false,
      "graph:Open graph view": false,
      "canvas:Create new canvas": false,
      "templates:Insert template": false,
      "command-palette:Open command palette": false
    }
  },
  "active": "1d366ad5f97b089f",
  "lastOpenFiles": [
    "Prefix-tree.md",
    "Suffix-tree.md",
    "Trie.md",
    "daily-notes/2023-06-19.md",
    "permanent-notes/Quadratic-functions.md",
    "String.md",
    "Sliding-window.md",
    "Array.md",
    "Index-as-hash-key.md",
    "Pre-computation.md",
    "Sorting.md",
    "Traverse-from-right.md",
    "Two-pointers.md",
    "daily-notes/2023-06-18.md",
    "Data-Structures.md",
    "permanent-notes/Algorithms.md",
    "templates/hub.md",
    "daily-notes/2023-06-17.md",
    "daily-notes/2023-06-14.md",
    "daily-notes/2023-06-13.md",
    "permanent-notes/Programs.md",
    "Strategy-Pattern.md",
    "Kubernetes-Pods.md",
    "Kubernetes-Deployments.md",
    "daily-notes/2023-04-18.md",
    "Untitled.md",
    "daily-notes",
    "Untitled.canvas",
    "permanent-notes",
    "daily-notes",
    "reference-notes",
    "templates",
    "assets"
  ]
}